gs_search_fedora_packages
