Metadata-Version: 1.0
Name: gnome-shell-search-fedora-packages
Version: 1.1.2
Summary: A gnome shell search provider for apps.fp.o/packages
Home-page: http://github.com/ralphbean/gnome-shell-search-fedora-packages
Author: Ralph Bean
Author-email: rbean@redhat.com
License: GPLv3
Platform: UNKNOWN
